awsspawner/__init__.py
awsspawner/awsspawner.py
jupyterhub_awsspawner-0.1.0.dist-info/LICENSE
jupyterhub_awsspawner-0.1.0.dist-info/WHEEL
jupyterhub_awsspawner-0.1.0.dist-info/METADATA
jupyterhub_awsspawner-0.1.0.dist-info/RECORD
